epubclozer/__main__.py
epubclozer-1.0.5.dist-info/METADATA
epubclozer-1.0.5.dist-info/WHEEL
epubclozer-1.0.5.dist-info/RECORD
