Metadata-Version: 2.1
Name: epubclozer
Version: 1.0.5
Summary: Turn an epub into Anki flashcards
Home-page: https://github.com/nelsontkq/epubclozer
Author: Nelson
Author-email: nelson@truran.dev
Requires-Python: >=3.11,<4.0
Classifier: Programming Language :: Python :: 3
Classifier: Programming Language :: Python :: 3.11
Requires-Dist: beautifulsoup4 (>=4.11.1,<5.0.0)
Requires-Dist: ebooklib (>=0.18,<0.19)
Requires-Dist: genanki (>=0.13.0,<0.14.0)
Requires-Dist: spacy (>=3.4.4,<4.0.0)
Project-URL: Repository, https://github.com/nelsontkq/epubclozer
